ofxstatement_equabankcz-1.0.0-py3.8-nspkg.pth
ofxstatement/plugins/equabankcz.py
ofxstatement_equabankcz-1.0.0.dist-info/LICENSE
ofxstatement_equabankcz-1.0.0.dist-info/METADATA
ofxstatement_equabankcz-1.0.0.dist-info/WHEEL
ofxstatement_equabankcz-1.0.0.dist-info/entry_points.txt
ofxstatement_equabankcz-1.0.0.dist-info/namespace_packages.txt
ofxstatement_equabankcz-1.0.0.dist-info/top_level.txt
ofxstatement_equabankcz-1.0.0.dist-info/zip-safe
ofxstatement_equabankcz-1.0.0.dist-info/RECORD
