Metadata-Version: 2.1
Name: ofxstatement-equabankcz
Version: 1.0.0
Summary: ofxstatement plugin for Equa Bank (CZ)
Home-page: https://github.com/kosciCZ/ofxstatement-equabankcz
Author: Jan Koscielniak
Author-email: jkosci@gmail.com
License: GPLv3
Keywords: ofx,banking,statement
Platform: UNKNOWN
Classifier: Development Status :: 3 - Alpha
Classifier: Programming Language :: Python :: 3
Classifier: Natural Language :: English
Classifier: Topic :: Office/Business :: Financial :: Accounting
Classifier: Topic :: Utilities
Classifier: Environment :: Console
Classifier: Operating System :: OS Independent
Classifier: License :: OSI Approved :: GNU General Public License v3 (GPLv3)
License-File: LICENSE
Requires-Dist: ofxstatement
